media/__init__.py
media/readme.txt
pyproject.toml
tracks/__init__.py
tracks/readme.txt
wkz/__init__.py
wkz/activity_views.py
wkz/admin.py
wkz/api.py
wkz/awards_views.py
wkz/best_sections/__init__.py
wkz/best_sections/climb.py
wkz/best_sections/fastest.py
wkz/best_sections/generic.py
wkz/configuration.py
wkz/demo.py
wkz/device/__init__.py
wkz/device/mount.py
wkz/forms.py
wkz/gis/__init__.py
wkz/gis/geo.py
wkz/initial_trace_data/2019-09-14-17-22-05.fit
wkz/initial_trace_data/2019-09-18-16-02-35.fit
wkz/initial_trace_data/2019-09-25-16-15-53.fit
wkz/initial_trace_data/2020-08-20-09-34-33.fit
wkz/initial_trace_data/2020-08-28-11-57-10.fit
wkz/initial_trace_data/2020-08-31-17-41-11.fit
wkz/initial_trace_data/2020-10-25-10-54-06.fit
wkz/initial_trace_data/__init__.py
wkz/initial_trace_data/cycling_bad_schandau.fit
wkz/initial_trace_data/cycling_walchensee.gpx
wkz/initial_trace_data/hike_with_coordinates_muggenbrunn.fit
wkz/io/__init__.py
wkz/io/auto_naming.py
wkz/io/file_importer.py
wkz/io/fit_collector.py
wkz/io/fit_parser.py
wkz/io/gpx_exporter.py
wkz/io/gpx_parser.py
wkz/io/parser.py
wkz/migrations/0001_squashed_0014_auto_20210112_1924.py
wkz/migrations/0002_auto_20210130_1351.py
wkz/migrations/0003_auto_20210218_2232.py
wkz/migrations/0004_settings_path_to_activities_on_device.py
wkz/migrations/0005_remove_settings_path_to_activities_on_device.py
wkz/migrations/0006_auto_20210321_1812.py
wkz/migrations/0007_auto_20210430_1633.py
wkz/migrations/0008_auto_20210611_0747.py
wkz/migrations/0009_auto_20211006_2053.py
wkz/migrations/0010_sport_mapping_name.py
wkz/migrations/__init__.py
wkz/models.py
wkz/plotting/__init__.py
wkz/plotting/plot_history.py
wkz/plotting/plot_pie_chart.py
wkz/plotting/plot_time_series.py
wkz/plotting/plot_trend.py
wkz/plotting/plot_workload.py
wkz/sport_views.py
wkz/static/css/paper-dashboard.css
wkz/static/css/paper-dashboard.css.map
wkz/static/css/paper-dashboard.min.css
wkz/static/img/bars.svg
wkz/static/img/dumpbell.png
workoutizer-0.25.1.dist-info/LICENSE
workoutizer-0.25.1.dist-info/METADATA
workoutizer-0.25.1.dist-info/WHEEL
workoutizer-0.25.1.dist-info/entry_points.txt
workoutizer-0.25.1.dist-info/RECORD
