Metadata-Version: 2.1
Name: workoutizer
Version: 0.25.1
Summary: 🏋️ Browser based Sport and Workout Organizer 🏃‍♀️
Home-page: https://github.com/fgebhart/workoutizer
Author: Fabian Gebhart
Requires-Python: >=3.8,<3.11
Classifier: Framework :: Django
Classifier: License :: OSI Approved :: MIT License
Classifier: Operating System :: MacOS
Classifier: Operating System :: POSIX :: Linux
Classifier: Programming Language :: Python
Classifier: Programming Language :: Python :: 3
Classifier: Programming Language :: Python :: 3.8
Classifier: Programming Language :: Python :: 3.9
Classifier: Programming Language :: Python :: 3.10
Requires-Dist: Jinja2 (>=3.0.3,<3.1.0)
Requires-Dist: Pillow (>=9.1.1,<10.0.0)
Requires-Dist: bokeh (==1.4.0)
Requires-Dist: channels (>=3.0.4,<4.0.0)
Requires-Dist: click (>=8.0.4,<9.0.0)
Requires-Dist: coloredlogs (>=15.0.1,<16.0.0)
Requires-Dist: django (>=4.0.6,<5.0.0)
Requires-Dist: django-colorfield (>=0.6.3,<0.7.0)
Requires-Dist: django-eventstream (>=4.4.0,<5.0.0)
Requires-Dist: djangorestframework (>=3.13.1,<4.0.0)
Requires-Dist: fitparse (>=1.2.0,<2.0.0)
Requires-Dist: geopy (>=2.1.0,<3.0.0)
Requires-Dist: gpxpy (>=1.5.0,<2.0.0)
Requires-Dist: haversine (>=2.5.1,<3.0.0)
Requires-Dist: huey (>=2.4.3,<3.0.0)
Requires-Dist: luddite (>=1.0.2,<2.0.0)
Requires-Dist: numpy (>=1.22.2,<2.0.0)
Requires-Dist: pandas (>=1.4.1,<2.0.0)
Requires-Dist: psutil (>=5.9.0,<6.0.0)
Requires-Dist: pyudev (>=0.23.2,<0.24.0)
Requires-Dist: sportgems (>=0.7.1,<0.8.0)
Requires-Dist: tenacity (>=8.0.1,<9.0.0)
Requires-Dist: tomli (>=2.0.1,<3.0.0)
Project-URL: Repository, https://github.com/fgebhart/workoutizer
